friendspy/qoutes/__init__.py
friendspy/quotes/__init__.py
friendspy-0.0.3.dist-info/METADATA
friendspy-0.0.3.dist-info/WHEEL
friendspy-0.0.3.dist-info/top_level.txt
friendspy-0.0.3.dist-info/RECORD
