Metadata-Version: 2.1
Name: friendspy
Version: 0.0.3
Summary: Friends Show Related API
Home-page: UNKNOWN
Author: Ashutosh Sharma
Author-email: email2ashusharma@gmail.com
License: UNKNOWN
Keywords: python,friends,entertainment,fun
Platform: UNKNOWN
Classifier: Development Status :: 1 - Planning
Classifier: Intended Audience :: Developers
Classifier: Programming Language :: Python :: 3
Classifier: Operating System :: Unix
Classifier: Operating System :: MacOS :: MacOS X
Classifier: Operating System :: Microsoft :: Windows
